UnrealAPI/__init__.py
UnrealAPI/test.py
UnrealAPI-0.1.dist-info/METADATA
UnrealAPI-0.1.dist-info/WHEEL
UnrealAPI-0.1.dist-info/top_level.txt
UnrealAPI-0.1.dist-info/RECORD
